nba_live/__init__.py
nba_live/datastream.py
nba_live/getboxscore.py
nba_live/getgamedata.py
nba_live/nbalive.py
nba_live-0.3.0.dist-info/METADATA
nba_live-0.3.0.dist-info/WHEEL
nba_live-0.3.0.dist-info/RECORD
